pipmaster/__init__.py
pipmaster/async_package_manager.py
pipmaster/package_manager.py
pipmaster/cli/__init__.py
pipmaster-1.0.7.dist-info/licenses/LICENSE
pipmaster-1.0.7.dist-info/METADATA
pipmaster-1.0.7.dist-info/WHEEL
pipmaster-1.0.7.dist-info/top_level.txt
pipmaster-1.0.7.dist-info/RECORD
