Metadata-Version: 2.4
Name: pipmaster
Version: 1.0.7
Summary: A versatile Python package manager utility for simplifying package installation, updates, checks, and environment management.
Author-email: ParisNeo <parisneoai@gmail.com>
License-Expression: Apache-2.0
Project-URL: Homepage, https://github.com/ParisNeo/pipmaster
Project-URL: Repository, https://github.com/ParisNeo/pipmaster
Project-URL: Issues, https://github.com/ParisNeo/pipmaster/issues
Keywords: pip,package manager,installer,dependency,venv,environment
Classifier: Development Status :: 4 - Beta
Classifier: Intended Audience :: Developers
Classifier: Programming Language :: Python :: 3.8
Classifier: Programming Language :: Python :: 3.9
Classifier: Programming Language :: Python :: 3.10
Classifier: Programming Language :: Python :: 3.11
Classifier: Programming Language :: Python :: 3.12
Classifier: Operating System :: OS Independent
Classifier: Topic :: Software Development :: Build Tools
Classifier: Topic :: System :: Software Distribution
Classifier: Typing :: Typed
Requires-Python: >=3.8
License-File: LICENSE
Requires-Dist: packaging>=21.0
Requires-Dist: ascii_colors>=0.8.0
Provides-Extra: audit
Requires-Dist: pip-audit>=2.5.0; extra == "audit"
Provides-Extra: dev
Requires-Dist: pytest>=7.0; extra == "dev"
Requires-Dist: pytest-asyncio>=0.20; extra == "dev"
Requires-Dist: pip-audit>=2.5.0; extra == "dev"
Requires-Dist: sphinx>=5.0; extra == "dev"
Requires-Dist: sphinx-rtd-theme>=1.0; extra == "dev"
Requires-Dist: myst-parser>=0.17; extra == "dev"
Requires-Dist: ruff>=0.1.0; extra == "dev"
Requires-Dist: mypy>=1.0; extra == "dev"
Requires-Dist: black; extra == "dev"
Requires-Dist: cowsay; extra == "dev"
Provides-Extra: all
Requires-Dist: pipmaster[audit]; extra == "all"
Requires-Dist: pipmaster[dev]; extra == "all"
Dynamic: license-file
